jury/__init__.py
jury/jury.py
jury/launcher.py
jury/timer.py
jury/utils/__init__.py
jury/utils/assertion.py
jury/utils/hidden_prints.py
jury/utils/logger.py
jury/utils/network.py
jury/utils/singleton.py
jury_test-0.0.3.dist-info/METADATA
jury_test-0.0.3.dist-info/WHEEL
jury_test-0.0.3.dist-info/entry_points.txt
jury_test-0.0.3.dist-info/license_files/LICENSE
jury_test-0.0.3.dist-info/RECORD
