Metadata-Version: 2.1
Name: jury-test
Version: 0.0.3
Summary: A black box testing tool
Project-URL: Bug Tracker, https://github.com/suxb201/Jury/issues
Project-URL: Homepage, https://github.com/suxb201/Jury
Author-email: suxb201 <suxb201@gmail.com>
Classifier: License :: OSI Approved :: MIT License
Classifier: Operating System :: OS Independent
Classifier: Programming Language :: Python :: 3
Requires-Python: >=3.9
Requires-Dist: rich>=12.4.4
